django_clear_memcache/__init__.py
django_clear_memcache/__init__.pyc
django_clear_memcache/admin.py
django_clear_memcache/apps.py
django_clear_memcache/apps.pyc
django_clear_memcache/clear.py
django_clear_memcache/models.py
django_clear_memcache/utility.py
django_clear_memcache/__pycache__/__init__.cpython-36.pyc
django_clear_memcache/__pycache__/__init__.cpython-37.pyc
django_clear_memcache/__pycache__/admin.cpython-36.pyc
django_clear_memcache/__pycache__/admin.cpython-37.pyc
django_clear_memcache/__pycache__/apps.cpython-36.pyc
django_clear_memcache/__pycache__/apps.cpython-37.pyc
django_clear_memcache/__pycache__/clear.cpython-36.pyc
django_clear_memcache/__pycache__/clear.cpython-37.pyc
django_clear_memcache/__pycache__/models.cpython-36.pyc
django_clear_memcache/__pycache__/models.cpython-37.pyc
django_clear_memcache/__pycache__/utility.cpython-36.pyc
django_clear_memcache/__pycache__/utility.cpython-37.pyc
django_clear_memcache/management/__init__.py
django_clear_memcache/management/__pycache__/__init__.cpython-36.pyc
django_clear_memcache/management/__pycache__/__init__.cpython-37.pyc
django_clear_memcache/management/commands/__init__.py
django_clear_memcache/management/commands/clear_memcache.py
django_clear_memcache/management/commands/__pycache__/__init__.cpython-37.pyc
django_clear_memcache/management/commands/__pycache__/clear_memcache.cpython-37.pyc
django_clear_memcache/static/admin/css/clear_memcache.css
django_clear_memcache/templates/admin/clear_memcache.html
django_clear_memcache-1.4.1.dist-info/LICENSE
django_clear_memcache-1.4.1.dist-info/METADATA
django_clear_memcache-1.4.1.dist-info/WHEEL
django_clear_memcache-1.4.1.dist-info/top_level.txt
django_clear_memcache-1.4.1.dist-info/RECORD
