Metadata-Version: 2.1
Name: django-clear-memcache
Version: 1.4.1
Summary: Allow to easily clear Memcache items in Django's admin interface.
Home-page: https://github.com/eht16/django-clear-memcache
Author: Enrico Tröger
Author-email: enrico.troeger@uvena.de
License: BSD
Download-URL: https://github.com/eht16/django-clear-memcache/archive/django-clear-memcache-1.4.1.tar.gz
Platform: UNKNOWN
Classifier: Development Status :: 4 - Beta
Classifier: Environment :: Web Environment
Classifier: Intended Audience :: Developers
Classifier: License :: OSI Approved :: BSD License
Classifier: Operating System :: OS Independent
Classifier: Programming Language :: Python
Classifier: Programming Language :: Python :: 2
Classifier: Programming Language :: Python :: 3
Classifier: Framework :: Django
Requires-Dist: django (>2.1)
